AUTHORS
LICENSE
MANIFEST.in
README.rst
setup.cfg
setup.py
txboto/__init__.py
txboto/auth.py
txboto/auth_handler.py
txboto/compat.py
txboto/connection.py
txboto/endpoints.json
txboto/exception.py
txboto/handler.py
txboto/httpcodes.py
txboto/plugin.py
txboto/provider.py
txboto/regioninfo.py
txboto/resultset.py
txboto/utils.py
txboto.egg-info/PKG-INFO
txboto.egg-info/SOURCES.txt
txboto.egg-info/dependency_links.txt
txboto.egg-info/not-zip-safe
txboto.egg-info/requires.txt
txboto.egg-info/top_level.txt
txboto/base/__init__.py
txboto/dynamodb/__init__.py
txboto/dynamodb/batch.py
txboto/dynamodb/condition.py
txboto/dynamodb/exceptions.py
txboto/dynamodb/item.py
txboto/dynamodb/layer1.py
txboto/dynamodb/layer2.py
txboto/dynamodb/schema.py
txboto/dynamodb/table.py
txboto/dynamodb/types.py
txboto/dynamodb2/__init__.py
txboto/dynamodb2/exceptions.py
txboto/dynamodb2/fields.py
txboto/dynamodb2/items.py
txboto/dynamodb2/layer1.py
txboto/dynamodb2/results.py
txboto/dynamodb2/table.py
txboto/dynamodb2/types.py
txboto/gs/__init__.py
txboto/gs/acl.py
txboto/gs/user.py
txboto/kinesis/__init__.py
txboto/kinesis/exceptions.py
txboto/kinesis/layer1.py
txboto/pyami/__init__.py
txboto/pyami/config.py
txboto/s3/__init__.py
txboto/s3/acl.py
txboto/s3/user.py